statinf/__init__.py
statinf/init_template.py
statinf/misc.py
statinf/data/GenerateData.py
statinf/data/ProcessData.py
statinf/data/__init__.py
statinf/distributions/__init__.py
statinf/distributions/continuous.py
statinf/distributions/discrete.py
statinf/ml/__init__.py
statinf/ml/activations.py
statinf/ml/generative.py
statinf/ml/initializations.py
statinf/ml/losses.py
statinf/ml/neuralnetwork.py
statinf/ml/optimizers.py
statinf/ml/performance.py
statinf/nonparametrics/__init__.py
statinf/nonparametrics/kernels.py
statinf/regressions/LinearModels.py
statinf/regressions/__init__.py
statinf/regressions/glm.py
statinf/regressions/glm_test.py
statinf/stats/__init__.py
statinf/stats/bayesian.py
statinf/stats/descriptive.py
statinf/stats/tests.py
statinf/stats/timeseries.py
statinf/stats/unsupervised.py
statinf-1.3.0.dist-info/LICENSE
statinf-1.3.0.dist-info/METADATA
statinf-1.3.0.dist-info/WHEEL
statinf-1.3.0.dist-info/top_level.txt
statinf-1.3.0.dist-info/RECORD
