Metadata-Version: 2.1
Name: statinf
Version: 1.3.0
Summary: A library for statistics and causal inference
Home-page: https://www.florianfelice.com/statinf
Author: Florian Felice
Author-email: florian.felice@outlook.com
Classifier: Programming Language :: Python :: 3
Classifier: License :: OSI Approved :: MIT License
Classifier: Operating System :: OS Independent
Requires-Python: >=3.6
License-File: LICENSE
Requires-Dist: jax >=0.2.10
Requires-Dist: jaxlib >=0.1.61
Requires-Dist: matplotlib >=3.1.1
Requires-Dist: numpy >=1.16.3
Requires-Dist: pandas >=0.24.1
Requires-Dist: pycof >=1.0.19
Requires-Dist: scipy >=1.2.1
